dbnomics_solr/__init__.py
dbnomics_solr/cli.py
dbnomics_solr/cli_utils.py
dbnomics_solr/collection_utils.py
dbnomics_solr/dbnomics_solr_client.py
dbnomics_solr/errors.py
dbnomics_solr/hash_utils.py
dbnomics_solr/py.typed
dbnomics_solr/text_utils.py
dbnomics_solr/types.py
dbnomics_solr/model/__init__.py
dbnomics_solr/model/counts.py
dbnomics_solr/services/__init__.py
dbnomics_solr/services/delete_dataset_docs.py
dbnomics_solr/services/delete_extra_datasets.py
dbnomics_solr/services/delete_provider_docs.py
dbnomics_solr/services/index_provider.py
dbnomics_solr/services/search_extra_datasets.py
dbnomics_solr/services/search_provider_datasets.py
dbnomics_solr/services/update_top_level_counts.py
dbnomics_solr-1.1.19.dist-info/LICENSE
dbnomics_solr-1.1.19.dist-info/METADATA
dbnomics_solr-1.1.19.dist-info/WHEEL
dbnomics_solr-1.1.19.dist-info/entry_points.txt
dbnomics_solr-1.1.19.dist-info/top_level.txt
dbnomics_solr-1.1.19.dist-info/RECORD
