Metadata-Version: 2.1
Name: dbnomics_solr
Version: 1.1.19
Summary: Index DBnomics data with Apache Solr for full-text and faceted search
Author-email: Christophe Benz <christophe.benz@nomics.world>
License: GNU AFFERO GENERAL PUBLIC LICENSE
Project-URL: Homepage, https://git.nomics.world/dbnomics/dbnomics-solr
Project-URL: Bug Tracker, https://git.nomics.world/dbnomics/dbnomics-solr/-/issues
Classifier: Programming Language :: Python :: 3
Classifier: License :: OSI Approved :: GNU Affero General Public License v3 or later (AGPLv3+)
Classifier: Operating System :: OS Independent
Requires-Python: >=3.9
License-File: LICENSE
Requires-Dist: daiquiri
Requires-Dist: dbnomics-data-model
Requires-Dist: dirhash
Requires-Dist: humanfriendly
Requires-Dist: orjson
Requires-Dist: pydantic
Requires-Dist: pysolr >=3.10.0
Requires-Dist: python-dotenv
Requires-Dist: python-slugify
Requires-Dist: requests
Requires-Dist: solrq
Requires-Dist: tenacity
Requires-Dist: typer[all]
Provides-Extra: dev
Requires-Dist: black ; extra == 'dev'
Requires-Dist: mypy ; extra == 'dev'
Requires-Dist: pre-commit ; extra == 'dev'
Requires-Dist: pytest ; extra == 'dev'
Requires-Dist: ruff ; extra == 'dev'
Requires-Dist: types-humanfriendly ; extra == 'dev'
Requires-Dist: types-python-slugify ; extra == 'dev'
Requires-Dist: types-requests ; extra == 'dev'
Requires-Dist: vermin ; extra == 'dev'
